{
  "deduplicationId": "e76a7bd1-25f4-4ce5-a6f5-49241aa92a75",
  "time": "2026-01-17T11:07:45.835+00:00",
  "deviceInfo": {
    "tenantId": "52f14cd4-c6f1-4fbd-8f87-4025e1d49242",
    "tenantName": "ChirpStack",
    "applicationId": "675582a5-5e7b-4e33-86ea-3325b7cb88e4",
    "applicationName": "L3",
    "deviceProfileId": "60ba97e4-d689-4a65-935a-acb5879b1239",
    "deviceProfileName": "Multitech RBS301 Temp Sensor",
    "deviceName": "Temp Sensor 05 - Unit #9",
    "devEui": "7894e80000054e0f",
    "deviceClassEnabled": "CLASS_A",
    "tags": {}
  },
  "devAddr": "0006b231",
  "adr": true,
  "dr": 3,
  "fCnt": 38643,
  "fPort": 1,
  "confirmed": false,
  "data": "GhkAHDA=",
  "object": {
    "eventType": "PERIODIC_REPORT",
    "temperature": 28,
    "humidity": 0
  },
  "rxInfo": [
    {
      "gatewayId": "008000000002aa4b",
      "uplinkId": 43005,
      "nsTime": "2026-01-17T11:07:45.905514134+00:00",
      "timeSinceGpsEpoch": "1452683283.835s",
      "rssi": -83,
      "snr": 9.8,
      "channel": 5,
      "rfChain": 1,
      "location": {
        "latitude": 61.35229,
        "longitude": -117.64841,
        "altitude": 161
      },
      "context": "QG98XA=="
    }
  ],
  "txInfo": {
    "frequency": 904900000,
    "modulation": {
      "lora": {
        "bandwidth": 125000,
        "spreadingFactor": 7,
        "codeRate": "CR_4_5"
      }
    }
  },
  "regionConfigId": "us915_1"
}