{
  "deduplicationId": "00ce5e09-de04-4813-b827-02020c6a04a2",
  "time": "2026-01-20T04:38:24.775+00:00",
  "deviceInfo": {
    "tenantId": "52f14cd4-c6f1-4fbd-8f87-4025e1d49242",
    "tenantName": "ChirpStack",
    "applicationId": "675582a5-5e7b-4e33-86ea-3325b7cb88e4",
    "applicationName": "L3",
    "deviceProfileId": "60ba97e4-d689-4a65-935a-acb5879b1239",
    "deviceProfileName": "Multitech RBS301 Temp Sensor",
    "deviceName": "Temp Sensor 05 - Unit #9",
    "devEui": "7894e80000054e0f",
    "deviceClassEnabled": "CLASS_A",
    "tags": {}
  },
  "devAddr": "0006b231",
  "adr": true,
  "dr": 3,
  "fCnt": 38958,
  "fPort": 1,
  "confirmed": false,
  "data": "HBkAGwA=",
  "object": {
    "eventType": "PERIODIC_REPORT",
    "humidity": 0,
    "temperature": 27
  },
  "rxInfo": [
    {
      "gatewayId": "008000000002aa4b",
      "uplinkId": 43570,
      "nsTime": "2026-01-20T04:38:24.863444783+00:00",
      "timeSinceGpsEpoch": "1452919122.775s",
      "rssi": -79,
      "snr": 9,
      "channel": 5,
      "rfChain": 1,
      "location": {
        "latitude": 61.35228,
        "longitude": -117.64843,
        "altitude": 132
      },
      "context": "dMXuHA=="
    }
  ],
  "txInfo": {
    "frequency": 904900000,
    "modulation": {
      "lora": {
        "bandwidth": 125000,
        "spreadingFactor": 7,
        "codeRate": "CR_4_5"
      }
    }
  },
  "regionConfigId": "us915_1"
}