{
  "deduplicationId": "09743683-99ee-4abf-a959-c4dbb8d881fd",
  "time": "2026-01-19T05:53:11.252+00:00",
  "deviceInfo": {
    "tenantId": "52f14cd4-c6f1-4fbd-8f87-4025e1d49242",
    "tenantName": "ChirpStack",
    "applicationId": "675582a5-5e7b-4e33-86ea-3325b7cb88e4",
    "applicationName": "L3",
    "deviceProfileId": "60ba97e4-d689-4a65-935a-acb5879b1239",
    "deviceProfileName": "Multitech RBS301 Temp Sensor",
    "deviceName": "Temp Sensor 05 - Unit #9",
    "devEui": "7894e80000054e0f",
    "deviceClassEnabled": "CLASS_A",
    "tags": {}
  },
  "devAddr": "0006b231",
  "adr": true,
  "dr": 3,
  "fCnt": 38859,
  "fPort": 1,
  "confirmed": false,
  "data": "HBkAGoA=",
  "object": {
    "humidity": 0,
    "eventType": "PERIODIC_REPORT",
    "temperature": 27
  },
  "rxInfo": [
    {
      "gatewayId": "008000000002aa4b",
      "uplinkId": 30906,
      "nsTime": "2026-01-19T05:53:11.324568112+00:00",
      "timeSinceGpsEpoch": "1452837209.252s",
      "rssi": -84,
      "snr": 9.5,
      "channel": 1,
      "location": {
        "latitude": 61.35228,
        "longitude": -117.64849,
        "altitude": 162
      },
      "context": "KFYrEw=="
    }
  ],
  "txInfo": {
    "frequency": 904100000,
    "modulation": {
      "lora": {
        "bandwidth": 125000,
        "spreadingFactor": 7,
        "codeRate": "CR_4_5"
      }
    }
  },
  "regionConfigId": "us915_1"
}