{
  "deduplicationId": "2094ad36-f80a-44c5-8656-7dddf8cd1ca3",
  "time": "2026-01-22T22:31:06.078+00:00",
  "deviceInfo": {
    "tenantId": "52f14cd4-c6f1-4fbd-8f87-4025e1d49242",
    "tenantName": "ChirpStack",
    "applicationId": "675582a5-5e7b-4e33-86ea-3325b7cb88e4",
    "applicationName": "L3",
    "deviceProfileId": "60ba97e4-d689-4a65-935a-acb5879b1239",
    "deviceProfileName": "Multitech RBS301 Temp Sensor",
    "deviceName": "T/H Sensor 04 - Northlands Trailer",
    "devEui": "7894e8000005874b",
    "deviceClassEnabled": "CLASS_A",
    "tags": {}
  },
  "devAddr": "00424d60",
  "adr": true,
  "dr": 3,
  "fCnt": 118,
  "fPort": 1,
  "confirmed": false,
  "data": "EQ0AHwAIMA==",
  "object": {
    "eventType": "PERIODIC_REPORT",
    "temperature": 31,
    "humidity": 8.3
  },
  "rxInfo": [
    {
      "gatewayId": "008000000002aa4b",
      "uplinkId": 6938,
      "nsTime": "2026-01-22T22:31:06.154352028+00:00",
      "timeSinceGpsEpoch": "1453156284.078s",
      "rssi": -105,
      "snr": 4.8,
      "channel": 2,
      "location": {
        "latitude": 61.35227,
        "longitude": -117.64847,
        "altitude": 146
      },
      "context": "+AGsEw=="
    }
  ],
  "txInfo": {
    "frequency": 904300000,
    "modulation": {
      "lora": {
        "bandwidth": 125000,
        "spreadingFactor": 7,
        "codeRate": "CR_4_5"
      }
    }
  },
  "regionConfigId": "us915_1"
}