{
  "deduplicationId": "8794c478-03eb-4250-b964-ec521909fcec",
  "time": "2026-01-22T16:26:29.736+00:00",
  "deviceInfo": {
    "tenantId": "52f14cd4-c6f1-4fbd-8f87-4025e1d49242",
    "tenantName": "ChirpStack",
    "applicationId": "66b43969-cb0f-4c60-a5bc-f95bfb2a357e",
    "applicationName": "Chris' Testing",
    "deviceProfileId": "f3e6c558-a212-439d-b834-193639f6f8b1",
    "deviceProfileName": "Makerfabs Soil Moisture Sensor",
    "deviceName": "John",
    "devEui": "48e663fffe3000df",
    "deviceClassEnabled": "CLASS_A",
    "tags": {}
  },
  "devAddr": "0069fa48",
  "regionConfigId": "us915_1"
}