{
  "deduplicationId": "a9bf474e-cacf-45a5-9a6a-1b5d337d4f8e",
  "time": "2026-01-24T05:29:37.964+00:00",
  "deviceInfo": {
    "tenantId": "52f14cd4-c6f1-4fbd-8f87-4025e1d49242",
    "tenantName": "ChirpStack",
    "applicationId": "675582a5-5e7b-4e33-86ea-3325b7cb88e4",
    "applicationName": "L3",
    "deviceProfileId": "60ba97e4-d689-4a65-935a-acb5879b1239",
    "deviceProfileName": "Multitech RBS301 Temp Sensor",
    "deviceName": "Temp Sensor 05 - Batchelor 1",
    "devEui": "7894e80000054e0b",
    "deviceClassEnabled": "CLASS_A",
    "tags": {}
  },
  "devAddr": "005c153e",
  "adr": true,
  "dr": 3,
  "fCnt": 8796,
  "fPort": 1,
  "confirmed": false,
  "data": "HBkAFRA=",
  "object": {
    "eventType": "PERIODIC_REPORT",
    "humidity": 0,
    "temperature": 21
  },
  "rxInfo": [
    {
      "gatewayId": "008000000002aa4b",
      "uplinkId": 33385,
      "nsTime": "2026-01-24T05:29:38.037375212+00:00",
      "timeSinceGpsEpoch": "1453267795.964s",
      "rssi": -71,
      "snr": 9,
      "channel": 1,
      "location": {
        "latitude": 61.35231,
        "longitude": -117.64839,
        "altitude": 147
      },
      "context": "xcChGw=="
    }
  ],
  "txInfo": {
    "frequency": 904100000,
    "modulation": {
      "lora": {
        "bandwidth": 125000,
        "spreadingFactor": 7,
        "codeRate": "CR_4_5"
      }
    }
  },
  "regionConfigId": "us915_1"
}