{
  "deduplicationId": "7138791f-8d7f-4be8-8d5e-d40be598b102",
  "time": "2026-01-17T12:42:57.243+00:00",
  "deviceInfo": {
    "tenantId": "52f14cd4-c6f1-4fbd-8f87-4025e1d49242",
    "tenantName": "ChirpStack",
    "applicationId": "675582a5-5e7b-4e33-86ea-3325b7cb88e4",
    "applicationName": "L3",
    "deviceProfileId": "60ba97e4-d689-4a65-935a-acb5879b1239",
    "deviceProfileName": "Multitech RBS301 Temp Sensor",
    "deviceName": "Temp Sensor 07 - Batchelor 1",
    "devEui": "7894e80000054e0b",
    "deviceClassEnabled": "CLASS_A",
    "tags": {}
  },
  "devAddr": "005c153e",
  "adr": true,
  "dr": 3,
  "fCnt": 8126,
  "fPort": 0,
  "confirmed": false,
  "data": "",
  "object": {
    "fPort": 0,
    "length": 0,
    "event": "Mac command"
  },
  "rxInfo": [
    {
      "gatewayId": "008000000002aa4b",
      "uplinkId": 48818,
      "nsTime": "2026-01-17T12:42:57.313511559+00:00",
      "timeSinceGpsEpoch": "1452688995.243s",
      "rssi": -85,
      "snr": 9.5,
      "channel": 3,
      "location": {
        "latitude": 61.35234,
        "longitude": -117.64851,
        "altitude": 157
      },
      "context": "MfEF4w=="
    }
  ],
  "txInfo": {
    "frequency": 904500000,
    "modulation": {
      "lora": {
        "bandwidth": 125000,
        "spreadingFactor": 7,
        "codeRate": "CR_4_5"
      }
    }
  },
  "regionConfigId": "us915_1"
}