{
  "deduplicationId": "32613c5f-0efe-4b0f-84f2-b72adb754cf3",
  "time": "2026-01-23T05:53:44.085+00:00",
  "deviceInfo": {
    "tenantId": "52f14cd4-c6f1-4fbd-8f87-4025e1d49242",
    "tenantName": "ChirpStack",
    "applicationId": "675582a5-5e7b-4e33-86ea-3325b7cb88e4",
    "applicationName": "L3",
    "deviceProfileId": "60ba97e4-d689-4a65-935a-acb5879b1239",
    "deviceProfileName": "Multitech RBS301 Temp Sensor",
    "deviceName": "T/H Sensor 01 - Lo's House",
    "devEui": "7894e8000005874f",
    "deviceClassEnabled": "CLASS_A",
    "tags": {}
  },
  "devAddr": "01e862ad",
  "adr": true,
  "dr": 3,
  "fCnt": 98,
  "fPort": 1,
  "confirmed": false,
  "data": "EA0AFXALUA==",
  "object": {
    "temperature": 21.7,
    "humidity": 11.5,
    "eventType": "PERIODIC_REPORT"
  },
  "rxInfo": [
    {
      "gatewayId": "008000000002aa4b",
      "uplinkId": 35430,
      "nsTime": "2026-01-23T05:53:44.157533141+00:00",
      "timeSinceGpsEpoch": "1453182842.085s",
      "rssi": -98,
      "snr": 9.2,
      "channel": 3,
      "location": {
        "latitude": 61.35234,
        "longitude": -117.64854,
        "altitude": 170
      },
      "context": "JvvE2w=="
    }
  ],
  "txInfo": {
    "frequency": 904500000,
    "modulation": {
      "lora": {
        "bandwidth": 125000,
        "spreadingFactor": 7,
        "codeRate": "CR_4_5"
      }
    }
  },
  "regionConfigId": "us915_1"
}