{
  "deduplicationId": "bc4e2b84-72ab-44d0-817f-6d5070503cbd",
  "time": "2026-01-25T11:23:48.844+00:00",
  "deviceInfo": {
    "tenantId": "52f14cd4-c6f1-4fbd-8f87-4025e1d49242",
    "tenantName": "ChirpStack",
    "applicationId": "675582a5-5e7b-4e33-86ea-3325b7cb88e4",
    "applicationName": "L3",
    "deviceProfileId": "60ba97e4-d689-4a65-935a-acb5879b1239",
    "deviceProfileName": "Multitech RBS301 Temp Sensor",
    "deviceName": "Temp Sensor 03 - Triplex Basement",
    "devEui": "7894e80000054e0a",
    "deviceClassEnabled": "CLASS_A",
    "tags": {}
  },
  "devAddr": "018a5a09",
  "adr": true,
  "dr": 3,
  "fCnt": 7512,
  "fPort": 1,
  "confirmed": false,
  "data": "FhkAFQA=",
  "object": {
    "temperature": 21,
    "humidity": 0,
    "eventType": "PERIODIC_REPORT"
  },
  "rxInfo": [
    {
      "gatewayId": "008000000002aa4b",
      "uplinkId": 20498,
      "nsTime": "2026-01-25T11:23:48.917681058+00:00",
      "timeSinceGpsEpoch": "1453375446.844s",
      "rssi": -104,
      "snr": 7.5,
      "channel": 1,
      "location": {
        "latitude": 61.35232,
        "longitude": -117.6484,
        "altitude": 152
      },
      "context": "rV+6aw=="
    }
  ],
  "txInfo": {
    "frequency": 904100000,
    "modulation": {
      "lora": {
        "bandwidth": 125000,
        "spreadingFactor": 7,
        "codeRate": "CR_4_5"
      }
    }
  },
  "regionConfigId": "us915_1"
}