{
  "deduplicationId": "aedc17d9-87c6-406a-bf9e-269cb2629c7b",
  "time": "2026-01-22T02:07:55.425+00:00",
  "deviceInfo": {
    "tenantId": "52f14cd4-c6f1-4fbd-8f87-4025e1d49242",
    "tenantName": "ChirpStack",
    "applicationId": "675582a5-5e7b-4e33-86ea-3325b7cb88e4",
    "applicationName": "L3",
    "deviceProfileId": "60ba97e4-d689-4a65-935a-acb5879b1239",
    "deviceProfileName": "Multitech RBS301 Temp Sensor",
    "deviceName": "Temp Sensor 03 - Triplex Basement",
    "devEui": "7894e80000054e0a",
    "deviceClassEnabled": "CLASS_A",
    "tags": {}
  },
  "devAddr": "018a5a09",
  "adr": true,
  "dr": 3,
  "fCnt": 7175,
  "fPort": 1,
  "confirmed": false,
  "data": "GxkAFIA=",
  "object": {
    "eventType": "PERIODIC_REPORT",
    "humidity": 0,
    "temperature": 21
  },
  "rxInfo": [
    {
      "gatewayId": "008000000002aa4b",
      "uplinkId": 22454,
      "nsTime": "2026-01-22T02:07:55.501928328+00:00",
      "timeSinceGpsEpoch": "1453082893.425s",
      "rssi": -104,
      "snr": 6.2,
      "location": {
        "latitude": 61.3523,
        "longitude": -117.64844,
        "altitude": 151
      },
      "context": "p4dW6w=="
    }
  ],
  "txInfo": {
    "frequency": 903900000,
    "modulation": {
      "lora": {
        "bandwidth": 125000,
        "spreadingFactor": 7,
        "codeRate": "CR_4_5"
      }
    }
  },
  "regionConfigId": "us915_1"
}