{
  "deduplicationId": "5d4a68ac-b860-4f56-ad32-24333f34cef4",
  "time": "2026-01-24T02:51:25.791+00:00",
  "deviceInfo": {
    "tenantId": "52f14cd4-c6f1-4fbd-8f87-4025e1d49242",
    "tenantName": "ChirpStack",
    "applicationId": "44e81855-d8ba-46c2-9e79-751913962e0f",
    "applicationName": "Kanata Monitoring",
    "deviceProfileId": "6c94d1f8-6bbb-42af-b877-253ecc501987",
    "deviceProfileName": "rbs305-ath",
    "deviceName": "ATH 1",
    "devEui": "7894e80000027a0a",
    "deviceClassEnabled": "CLASS_A",
    "tags": {}
  },
  "devAddr": "00baf539",
  "adr": true,
  "dr": 3,
  "fCnt": 2522,
  "fPort": 2,
  "confirmed": false,
  "data": "FQ0AF0AHYA==",
  "object": {
    "Protocol": 1,
    "Event": "Periodic Report",
    "humidity": 8,
    "Counter": 5,
    "Type": "ATH",
    "temperature": 23
  },
  "rxInfo": [
    {
      "gatewayId": "00800000a000e250",
      "uplinkId": 52130,
      "nsTime": "2026-01-24T02:51:25.866748748+00:00",
      "timeSinceGpsEpoch": "1453258303.791s",
      "rssi": -70,
      "snr": 12,
      "channel": 5,
      "rfChain": 1,
      "location": {
        "latitude": 45.34022,
        "longitude": -75.89888,
        "altitude": 85
      },
      "context": "AYnm2Q=="
    }
  ],
  "txInfo": {
    "frequency": 904900000,
    "modulation": {
      "lora": {
        "bandwidth": 125000,
        "spreadingFactor": 7,
        "codeRate": "CR_4_5"
      }
    }
  },
  "regionConfigId": "us915_1"
}