{
  "deduplicationId": "0f80f2a6-e69b-45aa-ac90-bc26b50262bc",
  "time": "2026-01-26T18:22:32.958+00:00",
  "deviceInfo": {
    "tenantId": "52f14cd4-c6f1-4fbd-8f87-4025e1d49242",
    "tenantName": "ChirpStack",
    "applicationId": "675582a5-5e7b-4e33-86ea-3325b7cb88e4",
    "applicationName": "L3",
    "deviceProfileId": "60ba97e4-d689-4a65-935a-acb5879b1239",
    "deviceProfileName": "Multitech RBS301 Temp Sensor",
    "deviceName": "Temp sensor 01 - Lo's Basement",
    "devEui": "7894e80000054e0e",
    "deviceClassEnabled": "CLASS_A",
    "tags": {}
  },
  "devAddr": "00dd821b",
  "adr": true,
  "dr": 3,
  "fCnt": 43,
  "fPort": 1,
  "confirmed": false,
  "data": "ExkAFSA=",
  "object": {
    "eventType": "PERIODIC_REPORT",
    "humidity": 0,
    "temperature": 21
  },
  "rxInfo": [
    {
      "gatewayId": "008000000002aa4b",
      "uplinkId": 35880,
      "nsTime": "2026-01-26T18:22:33.035718887+00:00",
      "timeSinceGpsEpoch": "1453486970.958s",
      "rssi": -106,
      "snr": 3.8,
      "channel": 5,
      "rfChain": 1,
      "location": {
        "latitude": 61.35226,
        "longitude": -117.64854,
        "altitude": 138
      },
      "context": "e9FKtA=="
    }
  ],
  "txInfo": {
    "frequency": 904900000,
    "modulation": {
      "lora": {
        "bandwidth": 125000,
        "spreadingFactor": 7,
        "codeRate": "CR_4_5"
      }
    }
  },
  "regionConfigId": "us915_1"
}