{
  "deduplicationId": "f124e589-409a-43cc-9b20-c8f5ca06688b",
  "time": "2026-01-20T17:08:29.352205327+00:00",
  "deviceInfo": {
    "tenantId": "52f14cd4-c6f1-4fbd-8f87-4025e1d49242",
    "tenantName": "ChirpStack",
    "applicationId": "5fe1c19e-491a-4968-9a4a-622c073e4a0c",
    "applicationName": "YK Testing",
    "deviceProfileId": "60ba97e4-d689-4a65-935a-acb5879b1239",
    "deviceProfileName": "Multitech RBS301 Temp Sensor",
    "deviceName": "NEW ATH 1",
    "devEui": "7894e80000054e0c",
    "deviceClassEnabled": "CLASS_A",
    "tags": {}
  },
  "devAddr": "010f8b0e",
  "adr": true,
  "dr": 3,
  "fCnt": 39340,
  "fPort": 1,
  "confirmed": false,
  "data": "EQEIADAAAAAAAAA=",
  "object": {
    "tamperState": 1,
    "errorWithLastDownlink": 0,
    "batteryLow": 0,
    "batteryLevel": 3,
    "radioCommError": 0,
    "tamperSinceLastReset": 0,
    "accumulationCount": 0
  },
  "rxInfo": [
    {
      "gatewayId": "0016c001f17adc38",
      "uplinkId": 3043857095,
      "nsTime": "2026-01-20T17:08:29.140602406+00:00",
      "rssi": -65,
      "snr": 13.75,
      "channel": 6,
      "rfChain": 1,
      "location": {},
      "context": "0kx75w==",
      "crcStatus": "CRC_OK"
    }
  ],
  "txInfo": {
    "frequency": 905100000,
    "modulation": {
      "lora": {
        "bandwidth": 125000,
        "spreadingFactor": 7,
        "codeRate": "CR_4_5"
      }
    }
  },
  "regionConfigId": "us915_1"
}