{
  "deduplicationId": "36635a9a-1db7-44c9-9e8e-540a4a463381",
  "time": "2026-01-23T15:23:52.732632585+00:00",
  "deviceInfo": {
    "tenantId": "52f14cd4-c6f1-4fbd-8f87-4025e1d49242",
    "tenantName": "ChirpStack",
    "applicationId": "5fe1c19e-491a-4968-9a4a-622c073e4a0c",
    "applicationName": "YK Testing",
    "deviceProfileId": "60ba97e4-d689-4a65-935a-acb5879b1239",
    "deviceProfileName": "Multitech RBS301 Temp Sensor",
    "deviceName": "NEW ATH 1",
    "devEui": "7894e80000054e0c",
    "deviceClassEnabled": "CLASS_A",
    "tags": {}
  },
  "devAddr": "010f8b0e",
  "adr": true,
  "dr": 3,
  "fCnt": 44603,
  "fPort": 1,
  "confirmed": false,
  "data": "HgEIADAAAAAAAAA=",
  "object": {
    "batteryLevel": 3,
    "tamperState": 1,
    "errorWithLastDownlink": 0,
    "tamperSinceLastReset": 0,
    "batteryLow": 0,
    "accumulationCount": 0,
    "radioCommError": 0
  },
  "rxInfo": [
    {
      "gatewayId": "0016c001f17adc38",
      "uplinkId": 1450486842,
      "nsTime": "2026-01-23T15:23:52.520097767+00:00",
      "rssi": -64,
      "snr": 10.75,
      "channel": 2,
      "location": {},
      "context": "tbHvFg==",
      "crcStatus": "CRC_OK"
    }
  ],
  "txInfo": {
    "frequency": 904300000,
    "modulation": {
      "lora": {
        "bandwidth": 125000,
        "spreadingFactor": 7,
        "codeRate": "CR_4_5"
      }
    }
  },
  "regionConfigId": "us915_1"
}